{
  "kind": "collectionType",
  "collectionName": "articles",
  "info": {
    "singularName": "article",
    "pluralName": "articles",
    "displayName": "Article",
    "description": "Blog articles with content, metadata, and relationships"
  },
  "options": {
    "draftAndPublish": true
  },
  "pluginOptions": {},
  "attributes": {
    "title": {
      "type": "string",
      "required": true,
      "maxLength": 255
    },
    "slug": {
      "type": "uid",
      "targetField": "title",
      "required": true
    },
    "excerpt": {
      "type": "text",
      "maxLength": 500
    },
    "content": {
      "type": "richtext",
      "required": true
    },
    "featuredImage": {
      "type": "media",
      "multiple": false,
      "required": false,
      "allowedTypes": ["images"]
    },
    "gallery": {
      "type": "media",
      "multiple": true,
      "required": false,
      "allowedTypes": ["images"]
    },
    "status": {
      "type": "enumeration",
      "enum": ["draft", "published", "archived"],
      "default": "draft"
    },
    "publishedAt": {
      "type": "datetime"
    },
    "readingTime": {
      "type": "integer",
      "min": 1
    },
    "viewCount": {
      "type": "integer",
      "default": 0,
      "min": 0
    },
    "isFeatured": {
      "type": "boolean",
      "default": false
    },
    "allowComments": {
      "type": "boolean",
      "default": true
    },
    "seoTitle": {
      "type": "string",
      "maxLength": 60
    },
    "seoDescription": {
      "type": "text",
      "maxLength": 160
    },
    "seoKeywords": {
      "type": "text"
    },
    "author": {
      "type": "relation",
      "relation": "manyToOne",
      "target": "api::author.author",
      "inversedBy": "articles"
    },
    "category": {
      "type": "relation",
      "relation": "manyToOne",
      "target": "api::category.category",
      "inversedBy": "articles"
    },
    "tags": {
      "type": "relation",
      "relation": "manyToMany",
      "target": "api::tag.tag"
    }
  }
}
